ISL/TP 3 - Fatoração em Verilog e Máximo Divisor Comum (MDC)/src/prime_factorization/hex_to_7seg.v
module hex_to_7seg(hex_digit, seg);
input [3:0] hex_digit;
output reg[6:0] seg;
//reg [6:0] seg;
// seg = {g,f,e,d,c,b,a};
// 0 is on and 1 is off

always @(hex_digit)
  case(hex_digit)
	  4'h0: seg = 7'b1000000;
	  4'h1: seg = 7'b1111001; 	// ---a----
	  4'h2: seg = 7'b0100100; 	// |	    |
	  4'h3: seg = 7'b0110000; 	// f	    b
	  4'h4: seg = 7'b0011001; 	// |	    |
	  4'h5: seg = 7'b0010010; 	// ---g----
	  4'h6: seg = 7'b0000010; 	// |	    |
	  4'h7: seg = 7'b1111000; 	// e	    c
	  4'h8: seg = 7'b0000000; 	// |	    |
	  4'h9: seg = 7'b0011000; 	// ---d----
	  4'ha: seg = 7'b0001000;
	  4'hb: seg = 7'b0000011;
	  4'hc: seg = 7'b1000110;
	  4'hd: seg = 7'b0100001;
	  4'he: seg = 7'b0000110;
	  4'hf: seg = 7'b0001110;
  endcase
endmodule

ISL/TP 3 - Fatoração em Verilog e Máximo Divisor Comum (MDC)/src/gcd_behavioral/bin_to_bcd.v
module bin_to_bcd (
    input [7:0] binary,
    output reg [3:0] tens,
    output reg [3:0] ones
  );

  integer i;
  always @(binary) begin
    tens = 4'd0;
    ones = 4'd0;

    for(i = 7; i >= 0; i = i - 1) begin
      if(tens >= 5)
        tens = tens + 3;
      if(ones >= 5)
        ones = ones + 3;

      tens = tens << 1;
      tens[0] = ones[3];
      ones = ones << 1;
      ones[0] = binary[i];
    end
  end
endmodule

ISL/TP 3 - Fatoração em Verilog e Máximo Divisor Comum (MDC)/src/prime_factorization/fatorador_engine.v
module fatorador_engine (
    input clk, reset,
    input start,
    input [15:0]in,
    output wire ready,
    output reg [15:0]out0,
    output reg [15:0]out1,
    output reg [15:0]out2,
    output reg [15:0]out3
  );

  // symbolic state declaration:
  localparam[2:0]
    idle = 2'b01,
    op   = 2'b10;

  // signal declaration:
  reg  [1:0]state_reg, state_next = idle;
  reg  [3:0]idx;
  reg [15:0]i, i_reg, i_next, i_mod, mod_next, primes_buff[3:0];
  // FSMD state and data registers:
  always @(posedge clk) begin
    if(reset) begin
      state_reg = idle;
      i_reg = 0;
    end else begin
      state_reg = state_next;
      i_reg = i_next;
      i_mod = mod_next;
    end
  end

  always @(i_reg or i) begin
    mod_next = i_reg % i;
  end

  // Next-state logic and data path functional unit:
  always @(in or i_reg or i_mod or state_reg) begin
    i_next = i_reg;
    state_next = state_reg;
    mod_next = i_mod;
    case(state_reg)
      idle: begin
        i = 2;
        i_next = in;
        state_next = op;
        for(idx = 0; idx < 4; idx = idx + 1) begin
          primes_buff[idx] = 88;
        end
        idx = 0;
      end

      op: begin
        if(i_next > 1) begin
          if(i_next%i == 0) begin
            i_next = i_next / i;
            if(idx > 0) begin
              if(primes_buff[idx - 1] !=  i) begin
                primes_buff[idx] = i;
                idx = idx + 1;  
              end
            end else begin
              primes_buff[idx] = i;
              idx = idx + 1;
            end
          end else begin
            i = i + 1;
          end
        end else begin
          out0 = primes_buff[0];
          out1 = primes_buff[1];
          out2 = primes_buff[2];
          out3 = primes_buff[3];
          state_next = idle;
        end
      end
    endcase
  end
endmodule

ISL/TP 3 - Fatoração em Verilog e Máximo Divisor Comum (MDC)/src/prime_factorization/fatorador_top.v
module fatorador_top (CLOCK_50, SW, HEX0, HEX1, HEX2, HEX3, HEX4, HEX5, HEX6, HEX7);
  input CLOCK_50;                                              // clock signal
  input  [15:0]SW;                                             // value to factorize 
  output [6:0]HEX0, HEX1, HEX2, HEX3, HEX4, HEX5, HEX6, HEX7;  // outputs display's

  wire ack;
  wire [3:0]dd0, dd1, dd2, dd3, dd4, dd5, dd6, dd7;
  reg  rst, req;
  integer cnt = 0;
  wire [15:0]disp0, disp1, disp2, disp3;
  
  always @(posedge CLOCK_50) begin
    if(cnt == 10) begin
      rst = 0;
      cnt = 10;
    end else begin
      rst = 1;
      cnt = cnt + 1;
    end
/*
    if(rst) begin
      req = 1;
    end else begin
      if(req) 
        req = 0;
      else
        if(ack) begin
          req = 1;
        end
    end
*/
  end

  //assign ready = ack;
  fatorador_engine fatorador_engine_00(CLOCK_50, rst, req, SW, ack, disp0, disp1, disp2, disp3);

  bin_to_bcd bin_to_bcd_01(disp0, dd1, dd0);
  hex_to_7seg hex_to_7seg_00(dd0, HEX0);    // tens
  hex_to_7seg hex_to_7seg_01(dd1, HEX1);    // ones

  bin_to_bcd bin_to_bcd_02(disp1, dd3, dd2);
  hex_to_7seg hex_to_7seg_02(dd2, HEX2);    // tens
  hex_to_7seg hex_to_7seg_03(dd3, HEX3);    // ones

  bin_to_bcd bin_to_bcd_03(disp2, dd5, dd4);
  hex_to_7seg hex_to_7seg_04(dd4, HEX4);    // tens
  hex_to_7seg hex_to_7seg_05(dd5, HEX5);    // ones

  bin_to_bcd bin_to_bcd_04(disp3, dd7, dd6);
  hex_to_7seg hex_to_7seg_06(dd6, HEX6);    // tens
  hex_to_7seg hex_to_7seg_07(dd7, HEX7);    // ones
endmodule

ISL/TP 3 - Fatoração em Verilog e Máximo Divisor Comum (MDC)/src/prime_factorization/testador.v
`timescale 1ns/100ps

/* Module to test your module fatorador */
module testador();

  // clock signal
  reg clock; 
  // number value tu be factorize       
  reg [15:0] value;  

  wire[6:0] hex0, hex1, hex2, hex3, hex4, hex5, hex6, hex7;

  // temp. values to print output
  reg[6:0] ohex0, ohex1, ohex2, ohex3, ohex4, ohex5, ohex6, ohex7;

  // 
  always
  begin
   # 10 clock = ~clock; // clock frecuency 10
  end

  always @(hex0, hex1, hex2, hex3, hex4, hex5, hex6, hex7) begin
    // task display used to convert to digit
    display(hex0, ohex0);
    display(hex1, ohex1);
    display(hex2, ohex2);
    display(hex3, ohex3);
    display(hex4, ohex4);
    display(hex5, ohex5);
    display(hex6, ohex6);
    display(hex7, ohex7);
    /*
      $display:
      This command prints a message on the screen when executed. 
      You can add a list of variables.The message must be declared in quotation marks (""),
      followed by the list of variables to be printed and the format.
       At the end of the message a carriage return is entered.
      Ex :      if ohex1 =0,ohex0=5
               $display("fator 1:",ohex1,ohex0); 
      output:
                   factor 1 : 0 5
    */
    $display("fator 1:",ohex1,ohex0);  
    $display("fator 2:",ohex3,ohex2);
    $display("fator 3:",ohex5,ohex4);
    $display("fator 4:",ohex7,ohex6);
  end

// ---------------------------------    display
/*
 Task to convert temp_in to number in ten base (temp_out)
*/
  task display;
  input [7:0] temp_in;    // input 
  output [7:0] temp_out;  // output (digit)
  begin
	  case(temp_in)
		  7'b1000000: temp_out = 0;
		  7'b1111001: temp_out = 1;
		  7'b0100100: temp_out = 2;
		  7'b0110000: temp_out = 3;
		  7'b0011001: temp_out = 4;
		  7'b0010010: temp_out = 5;
		  7'b0000010: temp_out = 6;
		  7'b1111000: temp_out = 7;
		  7'b0000000: temp_out = 8;
		  7'b0010000: temp_out = 9;
		  default: temp_out = -1;	
	  endcase
  end

  endtask
//---------------------------------------------------- end task
  initial begin
    clock = 0;
    value = 350;    // number to factorize
    #1000;
    value = 210;    // number to factorize
    #1000;
    value =  11;    // number to factorize
    #1000;
    value =  85;    // number to factorize
    #1000
    value =  5;     // number to factorize
    #1000
    value =  125;     // number to factorize
    #1000
    value =  115;     // number to factorize
    #1000
    value =  3;     // number to factorize
    #1000

    $finish;    // number to finish simulation
  end
  // module test

  fatorador_top f(clock, value, hex0, hex1, hex2, hex3, hex4, hex5, hex6, hex7);

  initial begin
    $dumpfile("fatorador_wave.vcd");
    $dumpvars;
  end 

/*-------------------------------
value = 350  
350 = 2 * 5^2 * 7

VSIM 11 >run
# fator 1:  0  2
# fator 2:  0  5
# fator 3:  0  7
# fator 4:  8  8

OUTPUT EXAMPLES

value = 210
210 = 2 * 3* 5* 7

VSIM 11 >run
# fator 1:  0  2
# fator 2:  0  3
# fator 3:  0  5
# fator 4:  0  7

//--------------------------------
value = 85  
85 = 5 * 17

VSIM 11 >run
# fator 1:  0  5
# fator 2:  1  7
# fator 3:  8  8
# fator 4:  8  8
-------------------------------*/
endmodule

ISL/TP 3 - Fatoração em Verilog e Máximo Divisor Comum (MDC)/src/prime_factorization/fatorador_wave.vcd
$date
	Wed Jun 22 23:45:20 2016
$end
$version
	Icarus Verilog
$end
$timescale
	100ps
$end
$scope module testador $end
$var wire 7 ! hex7 [6:0] $end
$var wire 7 " hex6 [6:0] $end
$var wire 7 # hex5 [6:0] $end
$var wire 7 $ hex4 [6:0] $end
$var wire 7 % hex3 [6:0] $end
$var wire 7 & hex2 [6:0] $end
$var wire 7 ' hex1 [6:0] $end
$var wire 7 ( hex0 [6:0] $end
$var reg 1 ) clock $end
$var reg 7 * ohex0 [6:0] $end
$var reg 7 + ohex1 [6:0] $end
$var reg 7 , ohex2 [6:0] $end
$var reg 7 - ohex3 [6:0] $end
$var reg 7 . ohex4 [6:0] $end
$var reg 7 / ohex5 [6:0] $end
$var reg 7 0 ohex6 [6:0] $end
$var reg 7 1 ohex7 [6:0] $end
$var reg 16 2 value [15:0] $end
$scope module f $end
$var wire 1 ) CLOCK_50 $end
$var wire 16 3 SW [15:0] $end
$var wire 1 4 ack $end
$var wire 16 5 disp3 [15:0] $end
$var wire 16 6 disp2 [15:0] $end
$var wire 16 7 disp1 [15:0] $end
$var wire 16 8 disp0 [15:0] $end
$var wire 4 9 dd7 [3:0] $end
$var wire 4 : dd6 [3:0] $end
$var wire 4 ; dd5 [3:0] $end
$var wire 4 < dd4 [3:0] $end
$var wire 4 = dd3 [3:0] $end
$var wire 4 > dd2 [3:0] $end
$var wire 4 ? dd1 [3:0] $end
$var wire 4 @ dd0 [3:0] $end
$var wire 7 A HEX7 [6:0] $end
$var wire 7 B HEX6 [6:0] $end
$var wire 7 C HEX5 [6:0] $end
$var wire 7 D HEX4 [6:0] $end
$var wire 7 E HEX3 [6:0] $end
$var wire 7 F HEX2 [6:0] $end
$var wire 7 G HEX1 [6:0] $end
$var wire 7 H HEX0 [6:0] $end
$var reg 1 I req $end
$var reg 1 J rst $end
$var integer 32 K cnt [31:0] $end
$scope module bin_to_bcd_01 $end
$var wire 8 L binary [7:0] $end
$var reg 4 M ones [3:0] $end
$var reg 4 N tens [3:0] $end
$var integer 32 O i [31:0] $end
$upscope $end
$scope module bin_to_bcd_02 $end
$var wire 8 P binary [7:0] $end
$var reg 4 Q ones [3:0] $end
$var reg 4 R tens [3:0] $end
$var integer 32 S i [31:0] $end
$upscope $end
$scope module bin_to_bcd_03 $end
$var wire 8 T binary [7:0] $end
$var reg 4 U ones [3:0] $end
$var reg 4 V tens [3:0] $end
$var integer 32 W i [31:0] $end
$upscope $end
$scope module bin_to_bcd_04 $end
$var wire 8 X binary [7:0] $end
$var reg 4 Y ones [3:0] $end
$var reg 4 Z tens [3:0] $end
$var integer 32 [ i [31:0] $end
$upscope $end
$scope module fatorador_engine_00 $end
$var wire 1 ) clk $end
$var wire 16 \ in [15:0] $end
$var wire 1 4 ready $end
$var wire 1 J reset $end
$var wire 1 I start $end
$var reg 16 ] i [15:0] $end
$var reg 16 ^ i_mod [15:0] $end
$var reg 16 _ i_next [15:0] $end
$var reg 16 ` i_reg [15:0] $end
$var reg 4 a idx [3:0] $end
$var reg 16 b mod_next [15:0] $end
$var reg 16 c out0 [15:0] $end
$var reg 16 d out1 [15:0] $end
$var reg 16 e out2 [15:0] $end
$var reg 16 f out3 [15:0] $end
$var reg 2 g state_next [1:0] $end
$var reg 2 h state_reg [1:0] $end
$upscope $end
$scope module hex_to_7seg_00 $end
$var wire 4 i hex_digit [3:0] $end
$var reg 7 j seg [6:0] $end
$upscope $end
$scope module hex_to_7seg_01 $end
$var wire 4 k hex_digit [3:0] $end
$var reg 7 l seg [6:0] $end
$upscope $end
$scope module hex_to_7seg_02 $end
$var wire 4 m hex_digit [3:0] $end
$var reg 7 n seg [6:0] $end
$upscope $end
$scope module hex_to_7seg_03 $end
$var wire 4 o hex_digit [3:0] $end
$var reg 7 p seg [6:0] $end
$upscope $end
$scope module hex_to_7seg_04 $end
$var wire 4 q hex_digit [3:0] $end
$var reg 7 r seg [6:0] $end
$upscope $end
$scope module hex_to_7seg_05 $end
$var wire 4 s hex_digit [3:0] $end
$var reg 7 t seg [6:0] $end
$upscope $end
$scope module hex_to_7seg_06 $end
$var wire 4 u hex_digit [3:0] $end
$var reg 7 v seg [6:0] $end
$upscope $end
$scope module hex_to_7seg_07 $end
$var wire 4 w hex_digit [3:0] $end
$var reg 7 x seg [6:0] $end
$upscope $end
$upscope $end
$scope task display $end
$var reg 8 y temp_in [7:0] $end
$var reg 8 z temp_out [7:0] $end
$upscope $end
$upscope $end
$enddefinitions $end
#0
$dumpvars
bx z
bx y
bx x
bx w
bx v
bx u
bx t
bx s
bx r
bx q
bx p
bx o
bx n
bx m
bx l
bx k
bx j
bx i
bx h
bx g
bx f
bx e
bx d
bx c
bx b
bx a
bx `
bx _
bx ^
bx ]
b101011110 \
bx [
bx Z
bx Y
bx X
bx W
bx V
bx U
bx T
bx S
bx R
bx Q
bx P
bx O
bx N
bx M
bx L
b0 K
xJ
xI
bx H
bx G
bx F
bx E
bx D
bx C
bx B
bx A
bx @
bx ?
bx >
bx =
bx <
bx ;
bx :
bx 9
bx 8
bx 7
bx 6
bx 5
z4
b101011110 3
b101011110 2
bx 1
bx 0
bx /
bx .
bx -
bx ,
bx +
bx *
0)
bx (
bx '
bx &
bx %
bx $
bx #
bx "
bx !
$end
#100
b0 b
b0 a
b10 ]
b10 g
b101011110 _
b0 `
b1 h
b1 K
1J
1)
#200
0)
#300
b10 K
1)
#400
0)
#500
b11 K
1)
#600
0)
#700
b100 K
1)
#800
0)
#900
b101 K
1)
#1000
0)
#1100
b110 K
1)
#1200
0)
#1300
b111 K
1)
#1400
0)
#1500
b1000 K
1)
#1600
0)
#1700
b1001 K
1)
#1800
0)
#1900
b1010 K
1)
#2000
0)
#2100
b1 a
b10101111 _
b0 ^
b101011110 `
b10 h
0J
1)
#2200
0)
#2300
b11 ]
b1 b
b10101111 `
1)
#2400
0)
#2500
b11 b
b100 ]
b1 ^
1)
#2600
0)
#2700
b0 b
b101 ]
b11 ^
1)
#2800
0)
#2900
b10 a
b100011 _
b0 ^
1)
#3000
0)
#3100
b111 _
b100011 `
1)
#3200
0)
#3300
b110 ]
b1 b
b111 `
1)
#3400
0)
#3500
b0 b
b111 ]
b1 ^
1)
#3600
0)
#3700
b11 a
b1 _
b0 ^
1)
#3800
0)
#3900
b1000 1
b1000 0
b0 /
b111 .
b0 -
b101 ,
b0 +
b10 *
b1000 z
b0 y
b0 "
b0 B
b0 v
b0 !
b0 A
b0 x
b1111000 $
b1111000 D
b1111000 r
b1000000 #
b1000000 C
b1000000 t
b10010 &
b10010 F
b10010 n
b1000000 %
b1000000 E
b1000000 p
b100100 (
b100100 H
b100100 j
b1000000 '
b1000000 G
b1000000 l
b11111111111111111111111111111111 [
b1000 :
b1000 Y
b1000 u
b1000 9
b1000 Z
b1000 w
b11111111111111111111111111111111 W
b111 <
b111 U
b111 q
b0 ;
b0 V
b0 s
b11111111111111111111111111111111 S
b101 >
b101 Q
b101 m
b0 =
b0 R
b0 o
b11111111111111111111111111111111 O
b10 @
b10 M
b10 i
b0 ?
b0 N
b0 k
b1011000 X
b111 T
b101 P
b10 L
b1 g
b1011000 5
b1011000 f
b111 6
b111 e
b101 7
b101 d
b10 8
b10 c
b0 b
b1 `
1)
#4000
0)
#4100
b1 b
b0 a
b10 g
b101011110 _
b10 ]
b1 h
1)
#4200
0)
#4300
b0 b
b1 a
b10101111 _
b1 ^
b101011110 `
b10 h
1)
#4400
0)
#4500
b11 ]
b1 b
b0 ^
b10101111 `
1)
#4600
0)
#4700
b11 b
b100 ]
b1 ^
1)
#4800
0)
#4900
b0 b
b101 ]
b11 ^
1)
#5000
0)
#5100
b10 a
b100011 _
b0 ^
1)
#5200
0)
#5300
b111 _
b100011 `
1)
#5400
0)
#5500
b110 ]
b1 b
b111 `
1)
#5600
0)
#5700
b0 b
b111 ]
b1 ^
1)
#5800
0)
#5900
b11 a
b1 _
b0 ^
1)
#6000
0)
#6100
b1 g
b0 b
b1 `
1)
#6200
0)
#6300
b1 b
b0 a
b10 g
b101011110 _
b10 ]
b1 h
1)
#6400
0)
#6500
b0 b
b1 a
b10101111 _
b1 ^
b101011110 `
b10 h
1)
#6600
0)
#6700
b11 ]
b1 b
b0 ^
b10101111 `
1)
#6800
0)
#6900
b11 b
b100 ]
b1 ^
1)
#7000
0)
#7100
b0 b
b101 ]
b11 ^
1)
#7200
0)
#7300
b10 a
b100011 _
b0 ^
1)
#7400
0)
#7500
b111 _
b100011 `
1)
#7600
0)
#7700
b110 ]
b1 b
b111 `
1)
#7800
0)
#7900
b0 b
b111 ]
b1 ^
1)
#8000
0)
#8100
b11 a
b1 _
b0 ^
1)
#8200
0)
#8300
b1 g
b0 b
b1 `
1)
#8400
0)
#8500
b1 b
b0 a
b10 g
b101011110 _
b10 ]
b1 h
1)
#8600
0)
#8700
b0 b
b1 a
b10101111 _
b1 ^
b101011110 `
b10 h
1)
#8800
0)
#8900
b11 ]
b1 b
b0 ^
b10101111 `
1)
#9000
0)
#9100
b11 b
b100 ]
b1 ^
1)
#9200
0)
#9300
b0 b
b101 ]
b11 ^
1)
#9400
0)
#9500
b10 a
b100011 _
b0 ^
1)
#9600
0)
#9700
b111 _
b100011 `
1)
#9800
0)
#9900
b110 ]
b1 b
b111 `
1)
#10000
b111 ]
b0 b
0)
b11010010 2
b11010010 3
b11010010 \
