ISL/TP 3 - Fatoração em Verilog e Máximo Divisor Comum (MDC)/src/gcd_behavioral/gcd_engine.v
module gcd_engine (
    input wire clk, reset,
    input wire start,
    input wire [6:0]a_in, b_in,
    output wire ready,
    output reg [6:0]r
  );

  // symbolic state declaration:
  localparam[1:0]
    idle = 2'b01,
    op   = 2'b10;

  // Signal declaration:
  reg [1:0]state_reg, state_next;
  reg [6:0]swap, a_reg, a_next, b_reg, b_next;

  // FSMD state and data registers:
  always @(posedge clk) begin
    if(reset) begin
      state_reg = idle;
      a_reg = 0;
      b_reg = 0;
    end else begin
      state_reg = state_next;
      a_reg = a_next;
      b_reg = b_next;
    end
  end

  // Next-state logic and data path functional unit:
  always @(a_reg or b_reg or state_reg) begin
    a_next = a_reg;
    b_next = b_reg;
    state_next = state_reg;
    case(state_reg)
      idle: begin
        if(start) begin
          a_next = a_in;
          b_next = b_in;
          state_next = op;
        end
      end
      op: begin
        if(a_next < b_next) begin
          swap   = a_next;
          a_next = b_next;
          b_next = swap;
        end else if(b_next != 0) begin
          a_next = a_next - b_next;
        end else begin
          r = a_next;
          state_next = idle;
        end
	   end
    endcase
  end
  
  assign ready = (state_reg == idle);
endmodule

ISL/TP 3 - Fatoração em Verilog e Máximo Divisor Comum (MDC)/src/gcd_behavioral/hex_to_7seg.v
module hex_to_7seg(hex_digit, seg);
input [3:0] hex_digit;
output [6:0] seg;
reg [6:0] seg;
// seg = {g,f,e,d,c,b,a};
// 0 is on and 1 is off

always @(hex_digit)
  case(hex_digit)
	  4'h0: seg = 7'b1000000;
	  4'h1: seg = 7'b1111001; 	// ---a----
	  4'h2: seg = 7'b0100100; 	// |	    |
	  4'h3: seg = 7'b0110000; 	// f	    b
	  4'h4: seg = 7'b0011001; 	// |	    |
	  4'h5: seg = 7'b0010010; 	// ---g----
	  4'h6: seg = 7'b0000010; 	// |	    |
	  4'h7: seg = 7'b1111000; 	// e	    c
	  4'h8: seg = 7'b0000000; 	// |	    |
	  4'h9: seg = 7'b0011000; 	// ---d----
	  4'ha: seg = 7'b0001000;
	  4'hb: seg = 7'b0000011;
	  4'hc: seg = 7'b1000110;
	  4'hd: seg = 7'b0100001;
	  4'he: seg = 7'b0000110;
	  4'hf: seg = 7'b0001110;
  endcase
endmodule

ISL/TP 3 - Fatoração em Verilog e Máximo Divisor Comum (MDC)/src/gcd_behavioral/bin_to_bcd.v
module bin_to_bcd (
    input [7:0] binary,
    output reg [3:0] tens,
    output reg [3:0] ones
  );

  integer i;
  always @(binary) begin
    tens = 4'd0;
    ones = 4'd0;

    for(i = 7; i >= 0; i = i - 1) begin
      if(tens >= 5)
        tens = tens + 3;
      if(ones >= 5)
        ones = ones + 3;

      tens = tens << 1;
      tens[0] = ones[3];
      ones = ones << 1;
      ones[0] = binary[i];
    end
  end
endmodule

ISL/TP 3 - Fatoração em Verilog e Máximo Divisor Comum (MDC)/src/gcd_behavioral/gcd_top.v
module gcd_top(CLOCK_50, SW, done, HEX0, HEX1, HEX2, HEX3, HEX4, HEX5, HEX6, HEX7);
  input  CLOCK_50;                                            // main clock
  input  [17:0]SW;                                            // switches
  output [6:0]HEX0, HEX1, HEX2, HEX3, HEX4, HEX5, HEX6, HEX7; // 7-seg disp
  output done;

  wire ack;
  wire [3:0]disp[5:0];
  wire [6:0]disp7[5:0];
  wire [6:0]r_old, a_xi, b_xi;

  reg rst, req;
  reg [6:0]r;
  reg [9:0]cnt0 = 0;
    
  always @(posedge CLOCK_50) begin
    if(cnt0 == 10) begin
  		rst = 1'b0;
	  	cnt0 = 10;
	  end else begin
      rst = 1'b1;
  		cnt0 = cnt0 + 1;
	  end

    if(rst) begin
      req = 1'b1;
      r = 0;
    end else begin
      if(req) 
        req = 1'b0;
      else
        if(ack) begin
          req = 1'b1;
          r = r_old;
        end
    end
  end

  assign done = ack;

  // input a:
  bin_to_bcd bin_to_bcd_01({1'b0, SW[13:7]}, disp[5], disp[4]);
  hex_to_7seg hex_to_7seg_01(disp[5], disp7[5]); // tens
  hex_to_7seg hex_to_7seg_02(disp[4], disp7[4]); // ones
  assign HEX7 = SW[13:7] == 0 || SW[13:7] > 99 ? 7'b0000110 : disp7[5];
  assign HEX6 = SW[13:7] == 0 || SW[13:7] > 99 ? 7'b0101111 : disp7[4];

  // input b:
  bin_to_bcd bin_to_bcd_02({1'b0, SW[6:0]}, disp[3], disp[2]);
  hex_to_7seg hex_to_7seg_03(disp[3], disp7[3]); // tens
  hex_to_7seg hex_to_7seg_04(disp[2], disp7[2]); // ones
  assign HEX5 = SW[6:0] == 0 || SW[6:0] > 99 ? 7'b0000110 : disp7[3];
  assign HEX4 = SW[6:0] == 0 || SW[6:0] > 99 ? 7'b0101111 : disp7[2];

  // turn off hundred's and thousand's displays:
  assign HEX3 = 7'b1111111;
  assign HEX2 = 7'b1111111;

  // output:
  bin_to_bcd bin_to_bcd_03({1'b0, r}, disp[1], disp[0]);
  hex_to_7seg hex_to_7seg_05(disp[1], disp7[1]); // tens
  hex_to_7seg hex_to_7seg_06(disp[0], disp7[0]); // ones
  assign HEX1 = SW[6:0]  == 0 || SW[6:0] > 99 || 
                SW[13:7] == 0 || SW[13:7] > 99 ? 7'b0000110 : disp7[1];
  assign HEX0 = SW[6:0]  == 0 || SW[6:0] > 99 || 
                SW[13:7] == 0 || SW[13:7] > 99 ? 7'b0101111 : disp7[0];

  // gcd engine:
  assign a_xi = SW[13:7] == 0 ? 1 : SW[13:7];
  assign b_xi = SW[6:0]  == 0 ? 1 : SW[6:0];
  gcd_engine gcd_engine_01(CLOCK_50, rst, req, a_xi, b_xi, ack, r_old);
endmodule

ISL/TP 3 - Fatoração em Verilog e Máximo Divisor Comum (MDC)/src/gcd_behavioral/gcd_tb.v
`timescale 1ns/100ps

module gcd_tb();
  reg clk;
  wire done;
  reg  [6:0]i, j;
  wire [6:0]disp[7:0];
  //wire [6:0]y;

  initial begin
    clk = 1'b0;
    i = 1;
    j = 1;
  end

  always begin
    #1 clk = ~clk;
  end

  always @(posedge clk) begin
    j = j + 1;
    if(j > 15) begin
      i = i + 1;
      j = 1;
      if(i > 15) begin
        i = 1;
        $finish;
      end
    end
    $display("%d %d", i, j);
  wait(done);
  //wait(!done);
  end

  gcd_top gcd_top_01(clk, {i, j}, done, disp[0], disp[1], disp[2], disp[3], disp[4], disp[5], disp[6], disp[7]);

  initial begin
    $dumpfile("gcd_tb.vcd");
    $dumpvars;
  end 
endmodule

ISL/TP 3 - Fatoração em Verilog e Máximo Divisor Comum (MDC)/src/gcd_behavioral/gcd_tb.vcd
$date
	Wed Jun 22 23:45:32 2016
$end
$version
	Icarus Verilog
$end
$timescale
	100ps
$end
$scope module gcd_tb $end
$var wire 1 ! done $end
$var reg 1 " clk $end
$var reg 7 # i [6:0] $end
$var reg 7 $ j [6:0] $end
$scope module gcd_top_01 $end
$var wire 1 " CLOCK_50 $end
$var wire 7 % HEX2 [6:0] $end
$var wire 7 & HEX3 [6:0] $end
$var wire 18 ' SW [17:0] $end
$var wire 1 ! done $end
$var wire 7 ( r_old [6:0] $end
$var wire 7 ) b_xi [6:0] $end
$var wire 1 * ack $end
$var wire 7 + a_xi [6:0] $end
$var wire 7 , HEX7 [6:0] $end
$var wire 7 - HEX6 [6:0] $end
$var wire 7 . HEX5 [6:0] $end
$var wire 7 / HEX4 [6:0] $end
$var wire 7 0 HEX1 [6:0] $end
$var wire 7 1 HEX0 [6:0] $end
$var reg 10 2 cnt0 [9:0] $end
$var reg 7 3 r [6:0] $end
$var reg 1 4 req $end
$var reg 1 5 rst $end
$scope module bin_to_bcd_01 $end
$var wire 8 6 binary [7:0] $end
$var reg 4 7 ones [3:0] $end
$var reg 4 8 tens [3:0] $end
$var integer 32 9 i [31:0] $end
$upscope $end
$scope module bin_to_bcd_02 $end
$var wire 8 : binary [7:0] $end
$var reg 4 ; ones [3:0] $end
$var reg 4 < tens [3:0] $end
$var integer 32 = i [31:0] $end
$upscope $end
$scope module bin_to_bcd_03 $end
$var wire 8 > binary [7:0] $end
$var reg 4 ? ones [3:0] $end
$var reg 4 @ tens [3:0] $end
$var integer 32 A i [31:0] $end
$upscope $end
$scope module gcd_engine_01 $end
$var wire 7 B a_in [6:0] $end
$var wire 7 C b_in [6:0] $end
$var wire 1 " clk $end
$var wire 1 5 reset $end
$var wire 1 4 start $end
$var wire 1 * ready $end
$var reg 7 D a_next [6:0] $end
$var reg 7 E a_reg [6:0] $end
$var reg 7 F b_next [6:0] $end
$var reg 7 G b_reg [6:0] $end
$var reg 7 H r [6:0] $end
$var reg 2 I state_next [1:0] $end
$var reg 2 J state_reg [1:0] $end
$var reg 7 K swap [6:0] $end
$upscope $end
$scope module hex_to_7seg_01 $end
$var wire 4 L hex_digit [3:0] $end
$var reg 7 M seg [6:0] $end
$upscope $end
$scope module hex_to_7seg_02 $end
$var wire 4 N hex_digit [3:0] $end
$var reg 7 O seg [6:0] $end
$upscope $end
$scope module hex_to_7seg_03 $end
$var wire 4 P hex_digit [3:0] $end
$var reg 7 Q seg [6:0] $end
$upscope $end
$scope module hex_to_7seg_04 $end
$var wire 4 R hex_digit [3:0] $end
$var reg 7 S seg [6:0] $end
$upscope $end
$scope module hex_to_7seg_05 $end
$var wire 4 T hex_digit [3:0] $end
$var reg 7 U seg [6:0] $end
$upscope $end
$scope module hex_to_7seg_06 $end
$var wire 4 V hex_digit [3:0] $end
$var reg 7 W seg [6:0] $end
$upscope $end
$upscope $end
$upscope $end
$enddefinitions $end
#0
$dumpvars
bx W
bx V
bx U
b0xxx T
b1111001 S
b1 R
b1000000 Q
b0 P
b1111001 O
b1 N
b1000000 M
b0 L
bx K
bx J
bx I
bx H
bx G
bx F
bx E
bx D
b1 C
b1 B
b11111111111111111111111111111111 A
b0xxx @
bx ?
b0xxxxxxx >
b11111111111111111111111111111111 =
b0 <
b1 ;
b1 :
b11111111111111111111111111111111 9
b0 8
b1 7
b1 6
x5
x4
bx 3
b0 2
bx 1
bx 0
b1111001 /
b1000000 .
b1111001 -
b1000000 ,
b1 +
x*
b1 )
bx (
b10000001 '
b1111111 &
b1111111 %
b1 $
b1 #
0"
x!
$end
#10
b100100 /
b1000000 1
b1000000 0
b100100 S
b1000000 W
b1000000 U
b11111111111111111111111111111111 =
b10 ;
b10 R
b10 )
b10 C
b10 I
b1 F
b1 D
b11111111111111111111111111111111 A
b0 ?
b0 V
b0 @
b0 T
b10 :
b0 G
b0 E
1!
1*
b1 J
b0 >
b0 3
14
b1 2
15
b10000010 '
b10 $
1"
#20
0"
#30
b110000 /
b110000 S
b11111111111111111111111111111111 =
b11 ;
b11 R
b11 )
b11 C
b11 :
b10 2
b10000011 '
b11 $
1"
#40
0"
#50
b11001 /
b11001 S
b11111111111111111111111111111111 =
b100 ;
b100 R
b100 )
b100 C
b100 :
b10000100 '
b100 $
b11 2
1"
#60
0"
#70
b10010 /
b10010 S
b11111111111111111111111111111111 =
b101 ;
b101 R
b101 )
b101 C
b101 :
b100 2
b10000101 '
b101 $
1"
#80
0"
#90
b10 /
b10 S
b11111111111111111111111111111111 =
b110 ;
b110 R
b110 )
b110 C
b110 :
b10000110 '
b110 $
b101 2
1"
#100
0"
#110
b1111000 /
b1111000 S
b11111111111111111111111111111111 =
b111 ;
b111 R
b111 )
b111 C
b111 :
b110 2
b10000111 '
b111 $
1"
#120
0"
#130
b0 /
b0 S
b11111111111111111111111111111111 =
b1000 ;
b1000 R
b1000 )
b1000 C
b1000 :
b10001000 '
b1000 $
b111 2
1"
#140
0"
#150
b11000 /
b11000 S
b11111111111111111111111111111111 =
b1001 ;
b1001 R
b1001 )
b1001 C
b1001 :
b1000 2
b10001001 '
b1001 $
1"
#160
0"
#170
b1111001 .
b1000000 /
b1111001 Q
b1000000 S
b1 <
b1 P
b11111111111111111111111111111111 =
b0 ;
b0 R
b1010 )
b1010 C
b1010 :
b10001010 '
b1010 $
b1001 2
1"
#180
0"
#190
b1111001 /
b1111001 S
b1 ;
b1 R
b11111111111111111111111111111111 =
b1 <
b1 P
b1011 )
b1011 C
b1011 :
b1010 2
b10001011 '
b1011 $
1"
#200
0"
#210
b100100 /
b100100 S
b11111111111111111111111111111111 =
b10 ;
b10 R
b1 <
b1 P
b1100 )
b1100 C
b1100 :
b0 D
b10001100 '
b1100 $
b1 G
b1 E
0!
0*
b10 J
04
05
1"
#220
0"
#230
b0 F
b1 D
b0 K
b0 E
1"
#240
0"
#250
b1 I
b1 (
b1 H
b0 G
b1 E
1"
#260
0"
#270
b1111001 1
b1111001 W
b1 ?
b1 V
b11111111111111111111111111111111 A
b10 I
b1100 F
b1 >
b1 3
14
1!
1*
b1 J
1"
#280
0"
#290
b110000 /
b110000 S
b11111111111111111111111111111111 =
b11 ;
b11 R
b1 <
b1 P
b1101 )
b1101 C
b1 F
b1100 D
b1 K
b1101 :
b1100 G
0!
0*
b10 J
04
b10001101 '
b1101 $
1"
#300
0"
#310
b11001 /
b11001 S
b11111111111111111111111111111111 =
b100 ;
b100 R
b1 <
b1 P
b1110 )
b1110 C
b1110 :
b1011 D
b10001110 '
b1110 $
b1 G
b1100 E
1"
#320
0"
#330
b1010 D
b1011 E
1"
#340
0"
#350
b1001 D
b1010 E
1"
#360
0"
#370
b1000 D
b1001 E
1"
#380
0"
#390
b111 D
b1000 E
1"
#400
0"
#410
b110 D
b111 E
1"
#420
0"
#430
b101 D
b110 E
1"
#440
0"
#450
b100 D
b101 E
1"
#460
0"
#470
b11 D
b100 E
1"
#480
0"
#490
b10 D
b11 E
1"
#500
0"
#510
b1 D
b10 E
1"
#520
0"
#530
b0 D
b1 E
1"
#540
0"
#550
b0 F
b1 D
b0 K
b0 E
1"
#560
0"
#570
b1 I
b0 G
b1 E
1"
#580
0"
#590
b10 I
b1110 F
14
1!
1*
b1 J
1"
#600
0"
#610
b10010 /
b10010 S
b11111111111111111111111111111111 =
b101 ;
b101 R
b1 <
b1 P
b1111 )
b1111 C
b1 F
b1110 D
b1 K
b1111 :
b1110 G
0!
0*
b10 J
04
b10001111 '
b1111 $
1"
#620
0"
#630
b100100 -
b1111001 /
b1000000 .
b100100 O
b1111001 S
b1000000 Q
b11111111111111111111111111111111 9
b10 7
b10 N
b10 +
b10 B
b11111111111111111111111111111111 =
b1 ;
b1 R
b0 <
b0 P
b1 )
b1 C
b10 6
b1 :
b1101 D
b10 #
b100000001 '
b1 $
b1 G
b1110 E
1"
#640
0"
#650
b1100 D
b1101 E
1"
#660
0"
#670
b1011 D
b1100 E
1"
#680
0"
#690
b1010 D
b1011 E
1"
#700
0"
#710
b1001 D
b1010 E
1"
#720
0"
#730
b1000 D
b1001 E
1"
#740
0"
#750
b111 D
b1000 E
1"
#760
0"
#770
b110 D
b111 E
1"
#780
0"
#790
b101 D
b110 E
1"
#800
0"
#810
b100 D
b101 E
1"
#820
0"
#830
b11 D
b100 E
1"
#840
0"
#850
b10 D
b11 E
1"
#860
0"
#870
b1 D
b10 E
1"
#880
0"
#890
b0 D
b1 E
1"
#900
0"
#910
b0 F
b1 D
b0 K
b0 E
1"
#920
0"
#930
b1 I
b0 G
b1 E
1"
#940
0"
#950
b10 I
b1 F
b10 D
14
1!
1*
b1 J
1"
#960
0"
#970
b100100 /
b100100 S
b11111111111111111111111111111111 =
b10 ;
b10 R
b10 )
b10 C
b1 D
b10 :
b1 G
b10 E
0!
0*
b10 J
04
b100000010 '
b10 $
1"
#980
0"
#990
b110000 /
b110000 S
b11111111111111111111111111111111 =
b11 ;
b11 R
b11 )
b11 C
b11 :
b0 D
b100000011 '
b11 $
b1 E
1"
#1000
0"
#1010
b0 F
b1 D
b0 E
1"
#1020
0"
#1030
b1 I
b0 G
b1 E
1"
#1040
0"
#1050
1!
1*
b1 J
1"
#1060
0"
#1070
b11001 /
b11001 S
b11111111111111111111111111111111 =
b100 ;
b100 R
b100 )
b100 C
b100 :
14
b100000100 '
b100 $
1"
#1080
0"
#1090
b10010 /
b10010 S
b11111111111111111111111111111111 =
b101 ;
b101 R
b101 )
b101 C
b101 :
b100000101 '
b101 $
04
1"
#1100
0"
#1110
b10 /
b10 S
b11111111111111111111111111111111 =
b110 ;
b110 R
b110 )
b110 C
b110 :
14
b100000110 '
b110 $
1"
#1120
0"
#1130
b1111000 /
b1111000 S
b11111111111111111111111111111111 =
b111 ;
b111 R
b111 )
b111 C
b111 :
b100000111 '
b111 $
04
1"
#1140
0"
#1150
b0 /
b0 S
b11111111111111111111111111111111 =
b1000 ;
b1000 R
b1000 )
b1000 C
b1000 :
14
b100001000 '
b1000 $
1"
#1160
0"
#1170
b11000 /
b11000 S
b11111111111111111111111111111111 =
b1001 ;
b1001 R
b1001 )
b1001 C
b1001 :
b100001001 '
b1001 $
04
1"
#1180
0"
#1190
b1111001 .
b1000000 /
b1111001 Q
b1000000 S
b1 <
b1 P
b11111111111111111111111111111111 =
b0 ;
b0 R
b1010 )
b1010 C
b1010 :
14
b100001010 '
b1010 $
1"
#1200
0"
#1210
b1111001 /
b1111001 S
b1 ;
b1 R
b11111111111111111111111111111111 =
b1 <
b1 P
b1011 )
b1011 C
b1011 :
b100001011 '
b1011 $
04
1"
#1220
0"
#1230
b100100 /
b100100 S
b11111111111111111111111111111111 =
b10 ;
b10 R
b1 <
b1 P
b1100 )
b1100 C
b1100 :
14
b100001100 '
b1100 $
1"
#1240
0"
#1250
b110000 /
b110000 S
b11111111111111111111111111111111 =
b11 ;
b11 R
b1 <
b1 P
b1101 )
b1101 C
b1101 :
b100001101 '
b1101 $
04
1"
#1260
0"
#1270
b11001 /
b11001 S
b11111111111111111111111111111111 =
b100 ;
b100 R
b1 <
b1 P
b1110 )
b1110 C
b1110 :
14
b100001110 '
b1110 $
1"
#1280
0"
#1290
b10010 /
b10010 S
b11111111111111111111111111111111 =
b101 ;
b101 R
b1 <
b1 P
b1111 )
b1111 C
b1111 :
b100001111 '
b1111 $
04
1"
#1300
0"
#1310
b110000 -
b1111001 /
b1000000 .
b110000 O
b1111001 S
b1000000 Q
b11111111111111111111111111111111 9
b11 7
b11 N
b11 +
b11 B
b11111111111111111111111111111111 =
b1 ;
b1 R
b0 <
b0 P
b1 )
b1 C
b11 6
b1 :
14
b11 #
b110000001 '
b1 $
1"
#1320
0"
#1330
b100100 /
b100100 S
b11111111111111111111111111111111 =
b10 ;
b10 R
b10 )
b10 C
b10 :
b110000010 '
b10 $
04
1"
#1340
0"
#1350
b110000 /
b110000 S
b11111111111111111111111111111111 =
b11 ;
b11 R
b11 )
b11 C
b11 :
14
b110000011 '
b11 $
1"
#1360
0"
#1370
b11001 /
b11001 S
b11111111111111111111111111111111 =
b100 ;
b100 R
b100 )
b100 C
b100 :
b110000100 '
b100 $
04
1"
#1380
0"
#1390
b10010 /
b10010 S
b11111111111111111111111111111111 =
b101 ;
b101 R
b101 )
b101 C
b101 :
14
b110000101 '
b101 $
1"
#1400
0"
#1410
b10 /
b10 S
b11111111111111111111111111111111 =
b110 ;
b110 R
b110 )
b110 C
b110 :
b110000110 '
b110 $
04
1"
#1420
0"
#1430
b1111000 /
b1111000 S
b11111111111111111111111111111111 =
b111 ;
b111 R
b111 )
b111 C
b111 :
14
b110000111 '
b111 $
1"
#1440
0"
#1450
b0 /
b0 S
b11111111111111111111111111111111 =
b1000 ;
b1000 R
b1000 )
b1000 C
b1000 :
b110001000 '
b1000 $
04
1"
#1460
0"
#1470
b11000 /
b11000 S
b11111111111111111111111111111111 =
b1001 ;
b1001 R
b1001 )
b1001 C
b1001 :
14
b110001001 '
b1001 $
1"
#1480
0"
#1490
b1111001 .
b1000000 /
b1111001 Q
b1000000 S
b1 <
b1 P
b11111111111111111111111111111111 =
b0 ;
b0 R
b1010 )
b1010 C
b1010 :
b110001010 '
b1010 $
04
1"
#1500
0"
#1510
b1111001 /
b1111001 S
b1 ;
b1 R
b11111111111111111111111111111111 =
b1 <
b1 P
b1011 )
b1011 C
b1011 :
14
b110001011 '
b1011 $
1"
#1520
0"
#1530
b100100 /
b100100 S
b11111111111111111111111111111111 =
b10 ;
b10 R
b1 <
b1 P
b1100 )
b1100 C
b1100 :
b110001100 '
b1100 $
04
1"
#1540
0"
#1550
b110000 /
b110000 S
b11111111111111111111111111111111 =
b11 ;
b11 R
b1 <
b1 P
b1101 )
b1101 C
b1101 :
14
b110001101 '
b1101 $
1"
#1560
0"
#1570
b11001 /
b11001 S
b11111111111111111111111111111111 =
b100 ;
b100 R
b1 <
b1 P
b1110 )
b1110 C
b1110 :
b110001110 '
b1110 $
04
1"
#1580
0"
#1590
b10010 /
b10010 S
b11111111111111111111111111111111 =
b101 ;
b101 R
b1 <
b1 P
b1111 )
b1111 C
b1111 :
14
b110001111 '
b1111 $
1"
#1600
0"
#1610
b11001 -
b1111001 /
b1000000 .
b11001 O
b1111001 S
b1000000 Q
b11111111111111111111111111111111 9
b100 7
b100 N
b100 +
b100 B
b11111111111111111111111111111111 =
b1 ;
b1 R
b0 <
b0 P
b1 )
b1 C
b100 6
b1 :
b100 #
b1000000001 '
b1 $
04
1"
#1620
0"
#1630
b100100 /
b100100 S
b11111111111111111111111111111111 =
b10 ;
b10 R
b10 )
b10 C
b10 :
14
b1000000010 '
b10 $
1"
#1640
0"
#1650
b110000 /
b110000 S
b11111111111111111111111111111111 =
b11 ;
b11 R
b11 )
b11 C
b11 :
b1000000011 '
b11 $
04
1"
#1660
0"
#1670
b11001 /
b11001 S
b11111111111111111111111111111111 =
b100 ;
b100 R
b100 )
b100 C
b100 :
14
b1000000100 '
b100 $
1"
#1680
0"
#1690
b10010 /
b10010 S
b11111111111111111111111111111111 =
b101 ;
b101 R
b101 )
b101 C
b101 :
b1000000101 '
b101 $
04
1"
#1700
0"
#1710
b10 /
b10 S
b11111111111111111111111111111111 =
b110 ;
b110 R
b110 )
b110 C
b110 :
14
b1000000110 '
b110 $
1"
#1720
0"
#1730
b1111000 /
b1111000 S
b11111111111111111111111111111111 =
b111 ;
b111 R
b111 )
b111 C
b111 :
b1000000111 '
b111 $
04
1"
#1740
0"
#1750
b0 /
b0 S
b11111111111111111111111111111111 =
b1000 ;
b1000 R
b1000 )
b1000 C
b1000 :
14
b1000001000 '
b1000 $
1"
#1760
0"
#1770
b11000 /
b11000 S
b11111111111111111111111111111111 =
b1001 ;
b1001 R
b1001 )
b1001 C
b1001 :
b1000001001 '
b1001 $
04
1"
#1780
0"
#1790
b1111001 .
b1000000 /
b1111001 Q
b1000000 S
b1 <
b1 P
b11111111111111111111111111111111 =
b0 ;
b0 R
b1010 )
b1010 C
b1010 :
14
b1000001010 '
b1010 $
1"
#1800
0"
#1810
b1111001 /
b1111001 S
b1 ;
b1 R
b11111111111111111111111111111111 =
b1 <
b1 P
b1011 )
b1011 C
b1011 :
b1000001011 '
b1011 $
04
1"
#1820
0"
#1830
b100100 /
b100100 S
b11111111111111111111111111111111 =
b10 ;
b10 R
b1 <
b1 P
b1100 )
b1100 C
b1100 :
14
b1000001100 '
b1100 $
1"
#1840
0"
#1850
b110000 /
b110000 S
b11111111111111111111111111111111 =
b11 ;
b11 R
b1 <
b1 P
b1101 )
b1101 C
b1101 :
b1000001101 '
b1101 $
04
1"
#1860
0"
#1870
b11001 /
b11001 S
b11111111111111111111111111111111 =
b100 ;
b100 R
b1 <
b1 P
b1110 )
b1110 C
b1110 :
14
b1000001110 '
b1110 $
1"
#1880
0"
#1890
b10010 /
b10010 S
b11111111111111111111111111111111 =
b101 ;
b101 R
b1 <
b1 P
b1111 )
b1111 C
b1111 :
b1000001111 '
b1111 $
04
1"
#1900
0"
#1910
b10010 -
b1111001 /
b1000000 .
b10010 O
b1111001 S
b1000000 Q
b11111111111111111111111111111111 9
b101 7
b101 N
b101 +
b101 B
b11111111111111111111111111111111 =
b1 ;
b1 R
b0 <
b0 P
b1 )
b1 C
b101 6
b1 :
14
b101 #
b1010000001 '
b1 $
1"
#1920
0"
#1930
b100100 /
b100100 S
b11111111111111111111111111111111 =
b10 ;
b10 R
b10 )
b10 C
b10 :
b1010000010 '
b10 $
04
1"
#1940
0"
#1950
b110000 /
b110000 S
b11111111111111111111111111111111 =
b11 ;
b11 R
b11 )
b11 C
b11 :
14
b1010000011 '
b11 $
1"
#1960
0"
#1970
b11001 /
b11001 S
b11111111111111111111111111111111 =
b100 ;
b100 R
b100 )
b100 C
b100 :
b1010000100 '
b100 $
04
1"
#1980
0"
#1990
b10010 /
b10010 S
b11111111111111111111111111111111 =
b101 ;
b101 R
b101 )
b101 C
b101 :
14
b1010000101 '
b101 $
1"
#2000
0"
#2010
b10 /
b10 S
b11111111111111111111111111111111 =
b110 ;
b110 R
b110 )
b110 C
b110 :
b1010000110 '
b110 $
04
1"
#2020
0"
#2030
b1111000 /
b1111000 S
b11111111111111111111111111111111 =
b111 ;
b111 R
b111 )
b111 C
b111 :
14
b1010000111 '
b111 $
1"
#2040
0"
#2050
b0 /
b0 S
b11111111111111111111111111111111 =
b1000 ;
b1000 R
b1000 )
b1000 C
b1000 :
b1010001000 '
b1000 $
04
1"
#2060
0"
#2070
b11000 /
b11000 S
b11111111111111111111111111111111 =
b1001 ;
b1001 R
b1001 )
b1001 C
b1001 :
14
b1010001001 '
b1001 $
1"
#2080
0"
#2090
b1111001 .
b1000000 /
b1111001 Q
b1000000 S
b1 <
b1 P
b11111111111111111111111111111111 =
b0 ;
b0 R
b1010 )
b1010 C
b1010 :
b1010001010 '
b1010 $
04
1"
#2100
0"
#2110
b1111001 /
b1111001 S
b1 ;
b1 R
b11111111111111111111111111111111 =
b1 <
b1 P
b1011 )
b1011 C
b1011 :
14
b1010001011 '
b1011 $
1"
#2120
0"
#2130
b100100 /
b100100 S
b11111111111111111111111111111111 =
b10 ;
b10 R
b1 <
b1 P
b1100 )
b1100 C
b1100 :
b1010001100 '
b1100 $
04
1"
#2140
0"
#2150
b110000 /
b110000 S
b11111111111111111111111111111111 =
b11 ;
b11 R
b1 <
b1 P
b1101 )
b1101 C
b1101 :
14
b1010001101 '
b1101 $
1"
#2160
0"
#2170
b11001 /
b11001 S
b11111111111111111111111111111111 =
b100 ;
b100 R
b1 <
b1 P
b1110 )
b1110 C
b1110 :
b1010001110 '
b1110 $
04
1"
#2180
0"
#2190
b10010 /
b10010 S
b11111111111111111111111111111111 =
b101 ;
b101 R
b1 <
b1 P
b1111 )
b1111 C
b1111 :
14
b1010001111 '
b1111 $
1"
#2200
0"
#2210
b10 -
b1111001 /
b1000000 .
b10 O
b1111001 S
b1000000 Q
b11111111111111111111111111111111 9
b110 7
b110 N
b110 +
b110 B
b11111111111111111111111111111111 =
b1 ;
b1 R
b0 <
b0 P
b1 )
b1 C
b110 6
b1 :
b110 #
b1100000001 '
b1 $
04
1"
#2220
0"
#2230
b100100 /
b100100 S
b11111111111111111111111111111111 =
b10 ;
b10 R
b10 )
b10 C
b10 :
14
b1100000010 '
b10 $
1"
#2240
0"
#2250
b110000 /
b110000 S
b11111111111111111111111111111111 =
b11 ;
b11 R
b11 )
b11 C
b11 :
b1100000011 '
b11 $
04
1"
#2260
0"
#2270
b11001 /
b11001 S
b11111111111111111111111111111111 =
b100 ;
b100 R
b100 )
b100 C
b100 :
14
b1100000100 '
b100 $
1"
#2280
0"
#2290
b10010 /
b10010 S
b11111111111111111111111111111111 =
b101 ;
b101 R
b101 )
b101 C
b101 :
b1100000101 '
b101 $
04
1"
#2300
0"
#2310
b10 /
b10 S
b11111111111111111111111111111111 =
b110 ;
b110 R
b110 )
b110 C
b110 :
14
b1100000110 '
b110 $
1"
#2320
0"
#2330
b1111000 /
b1111000 S
b11111111111111111111111111111111 =
b111 ;
b111 R
b111 )
b111 C
b111 :
b1100000111 '
b111 $
04
1"
#2340
0"
#2350
b0 /
b0 S
b11111111111111111111111111111111 =
b1000 ;
b1000 R
b1000 )
b1000 C
b1000 :
14
b1100001000 '
b1000 $
1"
#2360
0"
#2370
b11000 /
b11000 S
b11111111111111111111111111111111 =
b1001 ;
b1001 R
b1001 )
b1001 C
b1001 :
b1100001001 '
b1001 $
04
1"
#2380
0"
#2390
b1111001 .
b1000000 /
b1111001 Q
b1000000 S
b1 <
b1 P
b11111111111111111111111111111111 =
b0 ;
b0 R
b1010 )
b1010 C
b1010 :
14
b1100001010 '
b1010 $
1"
#2400
0"
#2410
b1111001 /
b1111001 S
b1 ;
b1 R
b11111111111111111111111111111111 =
b1 <
b1 P
b1011 )
b1011 C
b1011 :
b1100001011 '
b1011 $
04
1"
#2420
0"
#2430
b100100 /
b100100 S
b11111111111111111111111111111111 =
b10 ;
b10 R
b1 <
b1 P
b1100 )
b1100 C
b1100 :
14
b1100001100 '
b1100 $
1"
#2440
0"
#2450
b110000 /
b110000 S
b11111111111111111111111111111111 =
b11 ;
b11 R
b1 <
b1 P
b1101 )
b1101 C
b1101 :
b1100001101 '
b1101 $
04
1"
#2460
0"
#2470
b11001 /
b11001 S
b11111111111111111111111111111111 =
b100 ;
b100 R
b1 <
b1 P
b1110 )
b1110 C
b1110 :
14
b1100001110 '
b1110 $
1"
#2480
0"
#2490
b10010 /
b10010 S
b11111111111111111111111111111111 =
b101 ;
b101 R
b1 <
b1 P
b1111 )
b1111 C
b1111 :
b1100001111 '
b1111 $
04
1"
#2500
0"
#2510
b1111000 -
b1111001 /
b1000000 .
b1111000 O
b1111001 S
b1000000 Q
b11111111111111111111111111111111 9
b111 7
b111 N
b111 +
b111 B
b11111111111111111111111111111111 =
b1 ;
b1 R
b0 <
b0 P
b1 )
b1 C
b111 6
b1 :
14
b111 #
b1110000001 '
b1 $
1"
#2520
0"
#2530
b100100 /
b100100 S
b11111111111111111111111111111111 =
b10 ;
b10 R
b10 )
b10 C
b10 :
b1110000010 '
b10 $
04
1"
#2540
0"
